{
  "posts": [
    {
      "mainDatas": {
        "data": "",
        "clientName": "testeeeeeeeeeeeeee",
        "addres": "",
        "equipamentName": "",
        "operator": "",
        "phone": "",
        "timeInitial": 0,
        "timeFinal": 0,
        "servicePay": false,
        "timePreco": 0,
        "obs": "",
        "fuel": "",
        "notes": ""
      },
      "id": 1
    },
    {
      "mainDatas": {
        "data": "2022-11-02",
        "clientName": "casdasda",
        "addres": "",
        "equipamentName": "",
        "operator": "",
        "phone": "",
        "timeInitial": 0,
        "timeFinal": 0,
        "servicePay": false,
        "timePreco": 0,
        "obs": "",
        "fuel": "",
        "notes": ""
      },
      "id": 2
    }
  ]
}